Workbook
Name Aporte: Investimentos!$E$16:$E$16
Name Aporte_VersaoFinal: 'Simulador de Investimentos'!$C$16:$C$16
Name Patrimonio: Investimentos!$E$19:$E$19
Name Patrimonio_VersaoFinal: 'Simulador de Investimentos'!$D$20:$D$20
Name Qtd_Anos: Investimentos!$E$17:$E$17
Name Qtd_Anos_VersaoFinal: 'Simulador de Investimentos'!$C$20:$C$20
Name QtdAnos_VersaoFinal: 'Simulador de Investimentos'!$C$20:$C$20
Name Rendimento_Carteira: Investimentos!$C$31:$C$31
Name RendimentoCarteira_VersaoFinal: 'Simulador de Investimentos'!$D$16:$D$16
Name Salario: Investimentos!$C$30:$C$30
Name Salario_VersaoFinal: 'Simulador de Investimentos'!$B$16:$B$16
Name Sug_Invest: Investimentos!$C$32:$C$32
Name Sugestao_Investimento: Investimentos!$C$32:$C$32
Name Taxa_Mensal: Investimentos!$E$18:$E$18
Name TaxaMensal_VersaoFinal: 'Simulador de Investimentos'!$B$20:$B$20

Sheet Simulador de Investimentos
B14: ⚙ CONFIGURAÇÕES
B15: Salário Mensal | C15: Aporte Mensal (30%) | D15: Rendimento Carteira | E15: Perfil
B16: 4800 | C16: {=Salario_VersaoFinal*30%} -> 1440 | D16: 0.006 | E16: Conservador
B18: 📊 MINHA PROJEÇÃO
B19: Taxa | C19: Prazo (Em anos) | D19: Patrimônio Acumulado | E19: Dividendos Mensais
B20: 0.01079 | C20: 10 | D20: {=FV(TaxaMensal_VersaoFinal,QtdAnos_VersaoFinal*12,Aporte_VersaoFinal*-1)} -> 350329.27 | E20: {=Patrimonio_VersaoFinal*RendimentoCarteira_VersaoFinal} -> 2101.9756
B22: CENÁRIOS
B23: Prazo | D23: Patrimônio Acumulado | E23: Dividendos Mensais
A24: 2 | C24: 2 Anos | D24: {=FV(TaxaMensal_VersaoFinal,$A24*12,Aporte_VersaoFinal*-1)} -> 39207.783 | E24: {=D24*RendimentoCarteira_VersaoFinal} -> 235.2467
A25: 5 | C25: 5 Anos | D25: {=FV(TaxaMensal_VersaoFinal,$A25*12,Aporte_VersaoFinal*-1)} -> 120638.76 | E25: {=D25*RendimentoCarteira_VersaoFinal} -> 723.83254
A26: 10 | C26: 10 Anos | D26: {=FV(TaxaMensal_VersaoFinal,$A26*12,Aporte_VersaoFinal*-1)} -> 350329.27 | E26: {=D26*RendimentoCarteira_VersaoFinal} -> 2101.9756
A27: 20 | C27: 20 Anos | D27: {=FV(TaxaMensal_VersaoFinal,$A27*12,Aporte_VersaoFinal*-1)} -> 1620285.7 | E27: {=D27*RendimentoCarteira_VersaoFinal} -> 9721.7142
A28: 30 | C28: 30 Anos | D28: {=FV(TaxaMensal_VersaoFinal,$A28*12,Aporte_VersaoFinal*-1)} -> 6223924.3 | E28: {=D28*RendimentoCarteira_VersaoFinal} -> 37343.546
B30: DISTRIBUIÇÃO DE APORTE
B48: TIPO DE FII | D48: Percentual Sugerido | E48: Valores
B49: PAPEL (Dívidas Imobiliárias) | D49: =VLOOKUP($E$16&"-"&B49,Técnico!$B:$E,4,FALSE) -> 0.3 | E49: =D49*$C$16 -> 432
B50: TIJOLO (Shoppings. prédios etc) | D50: =VLOOKUP($E$16&"-"&B50,Técnico!$B:$E,4,FALSE) -> 0.5 | E50: =D50*$C$16 -> 720
B51: HÍBRIDOS | D51: =VLOOKUP($E$16&"-"&B51,Técnico!$B:$E,4,FALSE) -> 0.1 | E51: =D51*$C$16 -> 144
B52: FOF's (Fundos de fundos) | D52: =VLOOKUP($E$16&"-"&B52,Técnico!$B:$E,4,FALSE) -> 0.1 | E52: =D52*$C$16 -> 144
B53: DESENVOLVIMENTO (Novas obras) | D53: =VLOOKUP($E$16&"-"&B53,Técnico!$B:$E,4,FALSE) -> 0 | E53: =D53*$C$16 -> 0
B54: HOTELARIA | D54: =VLOOKUP($E$16&"-"&B54,Técnico!$B:$E,4,FALSE) -> 0 | E54: =D54*$C$16 -> 0
D55: =SUM(D49:D54) -> 1 | E55: =SUM(E49:E54) -> 1440

Sheet Investimentos
B15: INVESTIMENTO MENSAL
B16: Quanto investir por mês? | E16: 1200
B17: Por quantos anos? | E17: 10
B18: Taxa de rendimento mensal? | E18: 0.01079
B19: Patrimônio acumulado? | E19: {=FV(Taxa_Mensal,Qtd_Anos*12,Aporte*-1)} -> 291941.06
B20: Dividendos mensais? | E20: {=Patrimonio*Rendimento_Carteira} -> 1751.6463
B22: CENÁRIOS | F22: DIVIDENDOS
A23: 2 | B23: Quantos em 02 anos? | E23: {=FV(Taxa_Mensal,$A23*12,Aporte*-1)} -> 32673.153 | F23: {=E23*Rendimento_Carteira} -> 196.03892
A24: 5 | B24: Quantos em 05 anos? | E24: {=FV(Taxa_Mensal,$A24*12,Aporte*-1)} -> 100532.3 | F24: {=E24*Rendimento_Carteira} -> 603.19378
A25: 10 | B25: Quantos em 10 anos? | E25: {=FV(Taxa_Mensal,$A25*12,Aporte*-1)} -> 291941.06 | F25: {=E25*Rendimento_Carteira} -> 1751.6463
A26: 20 | B26: Quantos em 20 anos? | E26: {=FV(Taxa_Mensal,$A26*12,Aporte*-1)} -> 1350238.1 | F26: {=E26*Rendimento_Carteira} -> 8101.4285
A27: 30 | B27: Quantos em 30 anos? | E27: {=FV(Taxa_Mensal,$A27*12,Aporte*-1)} -> 5186603.6 | F27: {=E27*Rendimento_Carteira} -> 31119.622
B29: CONFIGURAÇÕES
B30: Salário | C30: 4000
B31: Rendimento Carteira | C31: 0.006
B32: Sugestão de Investimento (30%) | C32: {=Salario*30%} -> 1200
B35: PERFIL | E35: Conservador
B36: VALOR A SER INVESTIDO POR MÊS | E36: {=Aporte} -> 1200
B38: TIPO DE FII | E38: Percentual Sugerido | F38: Valores
B39: PAPEL (Dívidas Imobiliárias) | E39: =VLOOKUP($E$35&"-"&B39,Técnico!$B:$E,4,FALSE) -> 0.3 | F39: =E39*$E$36 -> 360
B40: TIJOLO (Shoppings. prédios etc) | E40: =VLOOKUP($E$35&"-"&B40,Técnico!$B:$E,4,FALSE) -> 0.5 | F40: =E40*$E$36 -> 600
B41: HÍBRIDOS | E41: =VLOOKUP($E$35&"-"&B41,Técnico!$B:$E,4,FALSE) -> 0.1 | F41: =E41*$E$36 -> 120
B42: FOF's (Fundos de fundos) | E42: =VLOOKUP($E$35&"-"&B42,Técnico!$B:$E,4,FALSE) -> 0.1 | F42: =E42*$E$36 -> 120
B43: DESENVOLVIMENTO (Novas obras) | E43: =VLOOKUP($E$35&"-"&B43,Técnico!$B:$E,4,FALSE) -> 0 | F43: =E43*$E$36 -> 0
B44: HOTELARIA | E44: =VLOOKUP($E$35&"-"&B44,Técnico!$B:$E,4,FALSE) -> 0 | F44: =E44*$E$36 -> 0
F45: =SUM(F39:F44) -> 1200

Sheet Técnico
B2: CHAVE | C2: PERFIL | D2: TIPO DE FII | E2: % | I2: %
B3: =C3&"-"&D3 -> Conservador-PAPEL (Dívidas Imobiliárias) | C3: Conservador | D3: PAPEL (Dívidas Imobiliárias) | E3: 0.3 | H3: Moderado-TIJOLO (Shoppings. prédios etc) | I3: =VLOOKUP(H3,$B:$E,4,FALSE) -> 0.35
B4: =C4&"-"&D4 -> Conservador-TIJOLO (Shoppings. prédios etc) | C4: Conservador | D4: TIJOLO (Shoppings. prédios etc) | E4: 0.5
B5: =C5&"-"&D5 -> Conservador-HÍBRIDOS | C5: Conservador | D5: HÍBRIDOS | E5: 0.1
B6: =C6&"-"&D6 -> Conservador-FOF's (Fundos de fundos) | C6: Conservador | D6: FOF's (Fundos de fundos) | E6: 0.1
B7: =C7&"-"&D7 -> Conservador-DESENVOLVIMENTO (Novas obras) | C7: Conservador | D7: DESENVOLVIMENTO (Novas obras) | E7: 0
B8: =C8&"-"&D8 -> Conservador-HOTELARIA | C8: Conservador | D8: HOTELARIA | E8: 0
B9: =C9&"-"&D9 -> Moderado-PAPEL (Dívidas Imobiliárias) | C9: Moderado | D9: PAPEL (Dívidas Imobiliárias) | E9: 0.32
B10: =C10&"-"&D10 -> Moderado-TIJOLO (Shoppings. prédios etc) | C10: Moderado | D10: TIJOLO (Shoppings. prédios etc) | E10: 0.35
B11: =C11&"-"&D11 -> Moderado-HÍBRIDOS | C11: Moderado | D11: HÍBRIDOS | E11: 0.08
B12: =C12&"-"&D12 -> Moderado-FOF's (Fundos de fundos) | C12: Moderado | D12: FOF's (Fundos de fundos) | E12: 0.05
B13: =C13&"-"&D13 -> Moderado-DESENVOLVIMENTO (Novas obras) | C13: Moderado | D13: DESENVOLVIMENTO (Novas obras) | E13: 0.1
B14: =C14&"-"&D14 -> Moderado-HOTELARIA | C14: Moderado | D14: HOTELARIA | E14: 0.1
B15: =C15&"-"&D15 -> Agressivo-PAPEL (Dívidas Imobiliárias) | C15: Agressivo | D15: PAPEL (Dívidas Imobiliárias) | E15: 0.5
... B20: =C20&"-"&D20 -> Agressivo-HOTELARIA | C20: Agressivo | D20: HOTELARIA | E20: 0.1
